zhipuai_langchain/__init__.py
zhipuai_langchain-0.1.202402031501.dist-info/METADATA
zhipuai_langchain-0.1.202402031501.dist-info/WHEEL
zhipuai_langchain-0.1.202402031501.dist-info/top_level.txt
zhipuai_langchain-0.1.202402031501.dist-info/RECORD
